{"ZXTlOZRUA1R0smn7tQk5xQ==":"img-4004-1640x924.png","HE2zuE/za4fXC0WSdFrlvw==":"black-170x211.png","b9oh6BO17FQoQCPoHaIAqA==":"70432c59-ce1d-49ca-9f42-63a5a3d40893-828x1035.jpg","dHpQYAQoSI60ZEVGA1CkOg==":"70432c59-ce1d-49ca-9f42-63a5a3d40893-828x1035.jpeg","dr5tzdffX1sWkvIYIORcZg==":"image27.webp","lTaW1KIsilHDOCzswpcbqw==":"image27-1.webp","i2/tGA384otA9M72Fg5dWA==":"image27-2.webp","pwHvQNinG/9JDlgS2RsYJg==":"d4b0d639-41a3-465e-829f-b54b4d9e77a8-1076x1076.jpg","zOvtPdT5Xw+2kosZj5L+wA==":"img-3931-1076x1059.png","VVy2E6Ou9w0tquAfTXEclw==":"fer%20tattoo-1076x1335.png","geQ8tMbbmVXHGKDwVN448w==":"img-4051-1076x1331.png","Zu8+A/TdG0R5EgIGdItZZw==":"img_2382%2020-1076x1077.png","2SE6I3IUhHfPk4yTNHOnKQ==":"img-4053-506x499.png","eyXbkupZPzoAmptpG9viwQ==":"img-4052-506x500.png","3AKNAPYBshCCJyLjcPz8BQ==":"img-4044-506x621.png","rasQilgB+rX4QQPlcYuvkA==":"img-4055-506x620.png"}